ytkubevault/__init__.py
ytkubevault/vault.py
ytkubevault-0.2.4.dist-info/LICENSE
ytkubevault-0.2.4.dist-info/METADATA
ytkubevault-0.2.4.dist-info/WHEEL
ytkubevault-0.2.4.dist-info/top_level.txt
ytkubevault-0.2.4.dist-info/RECORD
