Metadata-Version: 2.1
Name: ytkubevault
Version: 0.2.4
Summary: A convenient wrapper for getting secrets from HashiCorp Vault in Kubernetes
Home-page: https://github.com/y-tree-limited/ytkubevault
Author: Wenru Dong
Author-email: wenru@y-tree.com
License: MIT License
Classifier: License :: OSI Approved :: MIT License
Classifier: Programming Language :: Python :: 3
Classifier: Programming Language :: Python :: 3.8
Classifier: Programming Language :: Python :: 3.9
Classifier: Programming Language :: Python :: 3.10
Classifier: Programming Language :: Python :: 3.11
Classifier: Operating System :: OS Independent
Classifier: Intended Audience :: Developers
Classifier: Topic :: Utilities
Requires-Python: >=3.8
License-File: LICENSE
Requires-Dist: hvac <2.0.0
Provides-Extra: dev
Requires-Dist: kubernetes >=26.1.0 ; extra == 'dev'
